pacroller/__init__.py
pacroller/analyze.py
pacroller/checker.py
pacroller/config.py
pacroller/known_output.py
pacroller/known_output_override.py
pacroller/mailer.py
pacroller/main.py
pacroller/news.py
pacroller/update-merge-config.py
pacroller/utils.py
pacroller-0.1.9.dist-info/LICENSE
pacroller-0.1.9.dist-info/METADATA
pacroller-0.1.9.dist-info/WHEEL
pacroller-0.1.9.dist-info/entry_points.txt
pacroller-0.1.9.dist-info/top_level.txt
pacroller-0.1.9.dist-info/RECORD
