Metadata-Version: 2.1
Name: pacroller
Version: 0.1.9
Summary: unattended upgrade for archlinux
Home-page: https://github.com/isjerryxiao/pacroller
Author: Jerry Xiao
Author-email: pacroller@mail.jerryxiao.cc
Classifier: Development Status :: 3 - Alpha
Classifier: Programming Language :: Python :: 3
Classifier: License :: OSI Approved :: GNU General Public License v3 (GPLv3)
Classifier: Operating System :: POSIX :: Linux
Requires-Python: >=3.12
License-File: LICENSE
Requires-Dist: pyalpm
